[
  {
    "year": 1972,
    "issue_date": null,
    "week": null,
    "song": "",
    "artist": ""
  },
  {
    "year": 1972,
    "issue_date": "1972-01-01",
    "week": "1972-01-01",
    "song": "Brand New Key",
    "artist": "Melanie"
  },
  {
    "year": 1972,
    "issue_date": "1972-01-15",
    "week": "1972-01-15",
    "song": "American Pie",
    "artist": "Don McLean"
  },
  {
    "year": 1972,
    "issue_date": "1972-02-12",
    "week": "1972-02-12",
    "song": "Let's Stay Together",
    "artist": "Al Green"
  },
  {
    "year": 1972,
    "issue_date": "1972-02-19",
    "week": "1972-02-19",
    "song": "Without You",
    "artist": "Nilsson"
  },
  {
    "year": 1972,
    "issue_date": "1972-03-18",
    "week": "1972-03-18",
    "song": "Heart of Gold",
    "artist": "Neil Young"
  },
  {
    "year": 1972,
    "issue_date": "1972-03-25",
    "week": "1972-03-25",
    "song": "A Horse with No Name",
    "artist": "America"
  },
  {
    "year": 1972,
    "issue_date": "1972-04-15",
    "week": "1972-04-15",
    "song": "The First Time Ever I Saw Your Face \"†",
    "artist": "Roberta Flack"
  },
  {
    "year": 1972,
    "issue_date": "1972-05-27",
    "week": "1972-05-27",
    "song": "Oh Girl",
    "artist": "The Chi-Lites"
  },
  {
    "year": 1972,
    "issue_date": "1972-06-03",
    "week": "1972-06-03",
    "song": "I'll Take You There",
    "artist": "The Staple Singers"
  },
  {
    "year": 1972,
    "issue_date": "1972-06-10",
    "week": "1972-06-10",
    "song": "The Candy Man",
    "artist": "Sammy Davis Jr."
  },
  {
    "year": 1972,
    "issue_date": "1972-07-01",
    "week": "1972-07-01",
    "song": "Song Sung Blue",
    "artist": "Neil Diamond"
  },
  {
    "year": 1972,
    "issue_date": "1972-07-08",
    "week": "1972-07-08",
    "song": "Lean on Me",
    "artist": "Bill Withers"
  },
  {
    "year": 1972,
    "issue_date": "1972-07-29",
    "week": "1972-07-29",
    "song": "Alone Again (Naturally)",
    "artist": "Gilbert O'Sullivan"
  },
  {
    "year": 1972,
    "issue_date": "1972-08-26",
    "week": "1972-08-26",
    "song": "Brandy (You're a Fine Girl)",
    "artist": "Looking Glass"
  },
  {
    "year": 1972,
    "issue_date": "1972-09-02",
    "week": "1972-09-02",
    "song": "Alone Again (Naturally)",
    "artist": "Gilbert O'Sullivan"
  },
  {
    "year": 1972,
    "issue_date": "1972-09-16",
    "week": "1972-09-16",
    "song": "Black and White",
    "artist": "Three Dog Night"
  },
  {
    "year": 1972,
    "issue_date": "1972-09-23",
    "week": "1972-09-23",
    "song": "Baby, Don't Get Hooked on Me",
    "artist": "Mac Davis"
  },
  {
    "year": 1972,
    "issue_date": "1972-10-14",
    "week": "1972-10-14",
    "song": "Ben",
    "artist": "Michael Jackson"
  },
  {
    "year": 1972,
    "issue_date": "1972-10-21",
    "week": "1972-10-21",
    "song": "My Ding-a-Ling",
    "artist": "Chuck Berry"
  },
  {
    "year": 1972,
    "issue_date": "1972-11-04",
    "week": "1972-11-04",
    "song": "I Can See Clearly Now",
    "artist": "Johnny Nash"
  },
  {
    "year": 1972,
    "issue_date": "1972-12-02",
    "week": "1972-12-02",
    "song": "Papa Was a Rollin' Stone",
    "artist": "The Temptations"
  },
  {
    "year": 1972,
    "issue_date": "1972-12-09",
    "week": "1972-12-09",
    "song": "I Am Woman",
    "artist": "Helen Reddy"
  },
  {
    "year": 1972,
    "issue_date": "1972-12-16",
    "week": "1972-12-16",
    "song": "Me and Mrs. Jones",
    "artist": "Billy Paul"
  }
]