[
  {
    "year": 2016,
    "issue_date": null,
    "week": null,
    "song": "",
    "artist": ""
  },
  {
    "year": 2016,
    "issue_date": "2016-01-02",
    "week": "2016-01-02",
    "song": "Hello",
    "artist": "Adele"
  },
  {
    "year": 2016,
    "issue_date": "2016-01-23",
    "week": "2016-01-23",
    "song": "Sorry",
    "artist": "Justin Bieber"
  },
  {
    "year": 2016,
    "issue_date": "2016-02-13",
    "week": "2016-02-13",
    "song": "Love Yourself \" †",
    "artist": "[ 15 ] [ 16 ]"
  },
  {
    "year": 2016,
    "issue_date": "2016-02-20",
    "week": "2016-02-20",
    "song": "Pillowtalk",
    "artist": "Zayn"
  },
  {
    "year": 2016,
    "issue_date": "2016-02-27",
    "week": "2016-02-27",
    "song": "Love Yourself\" †",
    "artist": "Justin Bieber"
  },
  {
    "year": 2016,
    "issue_date": "2016-03-05",
    "week": "2016-03-05",
    "song": "Work",
    "artist": "Rihanna featuring Drake"
  },
  {
    "year": 2016,
    "issue_date": "2016-05-07",
    "week": "2016-05-07",
    "song": "Panda",
    "artist": "Desiigner"
  },
  {
    "year": 2016,
    "issue_date": "2016-05-21",
    "week": "2016-05-21",
    "song": "One Dance",
    "artist": "Drake featuring Wizkid and Kyla"
  },
  {
    "year": 2016,
    "issue_date": "2016-05-28",
    "week": "2016-05-28",
    "song": "Can't Stop the Feeling!",
    "artist": "Justin Timberlake"
  },
  {
    "year": 2016,
    "issue_date": "2016-06-04",
    "week": "2016-06-04",
    "song": "One Dance",
    "artist": "Drake featuring Wizkid and Kyla"
  },
  {
    "year": 2016,
    "issue_date": "2016-08-06",
    "week": "2016-08-06",
    "song": "Cheap Thrills",
    "artist": "Sia featuring Sean Paul"
  },
  {
    "year": 2016,
    "issue_date": "2016-09-03",
    "week": "2016-09-03",
    "song": "Closer",
    "artist": "The Chainsmokers featuring Halsey"
  },
  {
    "year": 2016,
    "issue_date": "2016-11-26",
    "week": "2016-11-26",
    "song": "Black Beatles",
    "artist": "Rae Sremmurd featuring Gucci Mane"
  }
]