[
  {
    "year": 2023,
    "issue_date": null,
    "week": null,
    "song": "Song",
    "artist": "Artist(s)",
    "source": "https://en.wikipedia.org/wiki/List_of_Billboard_Hot_100_number_ones_of_2023",
    "row_index": 0
  },
  {
    "year": 2023,
    "issue_date": "2023-01-07",
    "week": "2023-01-07",
    "song": "All I Want for Christmas Is You",
    "artist": "Mariah Carey",
    "source": "https://en.wikipedia.org/wiki/List_of_Billboard_Hot_100_number_ones_of_2023",
    "row_index": 1
  },
  {
    "year": 2023,
    "issue_date": "2023-01-14",
    "week": "2023-01-14",
    "song": "Anti-Hero",
    "artist": "Taylor Swift",
    "source": "https://en.wikipedia.org/wiki/List_of_Billboard_Hot_100_number_ones_of_2023",
    "row_index": 2
  },
  {
    "year": 2023,
    "issue_date": "2023-01-28",
    "week": "2023-01-28",
    "song": "Flowers",
    "artist": "Miley Cyrus",
    "source": "https://en.wikipedia.org/wiki/List_of_Billboard_Hot_100_number_ones_of_2023",
    "row_index": 3
  },
  {
    "year": 2023,
    "issue_date": "2023-03-11",
    "week": "2023-03-11",
    "song": "Die for You",
    "artist": "The Weeknd and Ariana Grande",
    "source": "https://en.wikipedia.org/wiki/List_of_Billboard_Hot_100_number_ones_of_2023",
    "row_index": 4
  },
  {
    "year": 2023,
    "issue_date": "2023-03-18",
    "week": "2023-03-18",
    "song": "Last Night \" †",
    "artist": "Morgan Wallen",
    "source": "https://en.wikipedia.org/wiki/List_of_Billboard_Hot_100_number_ones_of_2023",
    "row_index": 5
  },
  {
    "year": 2023,
    "issue_date": "2023-03-25",
    "week": "2023-03-25",
    "song": "Flowers",
    "artist": "Miley Cyrus",
    "source": "https://en.wikipedia.org/wiki/List_of_Billboard_Hot_100_number_ones_of_2023",
    "row_index": 6
  },
  {
    "year": 2023,
    "issue_date": "2023-04-08",
    "week": "2023-04-08",
    "song": "Like Crazy",
    "artist": "Jimin",
    "source": "https://en.wikipedia.org/wiki/List_of_Billboard_Hot_100_number_ones_of_2023",
    "row_index": 7
  },
  {
    "year": 2023,
    "issue_date": "2023-04-15",
    "week": "2023-04-15",
    "song": "Last Night\" †",
    "artist": "Morgan Wallen",
    "source": "https://en.wikipedia.org/wiki/List_of_Billboard_Hot_100_number_ones_of_2023",
    "row_index": 8
  },
  {
    "year": 2023,
    "issue_date": "2023-04-29",
    "week": "2023-04-29",
    "song": "Kill Bill",
    "artist": "SZA",
    "source": "https://en.wikipedia.org/wiki/List_of_Billboard_Hot_100_number_ones_of_2023",
    "row_index": 9
  },
  {
    "year": 2023,
    "issue_date": "2023-05-06",
    "week": "2023-05-06",
    "song": "Last Night\" †",
    "artist": "Morgan Wallen",
    "source": "https://en.wikipedia.org/wiki/List_of_Billboard_Hot_100_number_ones_of_2023",
    "row_index": 10
  },
  {
    "year": 2023,
    "issue_date": "2023-07-15",
    "week": "2023-07-15",
    "song": "Vampire",
    "artist": "Olivia Rodrigo",
    "source": "https://en.wikipedia.org/wiki/List_of_Billboard_Hot_100_number_ones_of_2023",
    "row_index": 11
  },
  {
    "year": 2023,
    "issue_date": "2023-07-22",
    "week": "2023-07-22",
    "song": "Last Night\" †",
    "artist": "Morgan Wallen",
    "source": "https://en.wikipedia.org/wiki/List_of_Billboard_Hot_100_number_ones_of_2023",
    "row_index": 12
  },
  {
    "year": 2023,
    "issue_date": "2023-07-29",
    "week": "2023-07-29",
    "song": "Seven",
    "artist": "Jung Kook featuring Latto",
    "source": "https://en.wikipedia.org/wiki/List_of_Billboard_Hot_100_number_ones_of_2023",
    "row_index": 13
  },
  {
    "year": 2023,
    "issue_date": "2023-08-05",
    "week": "2023-08-05",
    "song": "Try That in a Small Town",
    "artist": "Jason Aldean",
    "source": "https://en.wikipedia.org/wiki/List_of_Billboard_Hot_100_number_ones_of_2023",
    "row_index": 14
  },
  {
    "year": 2023,
    "issue_date": "2023-08-12",
    "week": "2023-08-12",
    "song": "Last Night\" †",
    "artist": "Morgan Wallen",
    "source": "https://en.wikipedia.org/wiki/List_of_Billboard_Hot_100_number_ones_of_2023",
    "row_index": 15
  },
  {
    "year": 2023,
    "issue_date": "2023-08-26",
    "week": "2023-08-26",
    "song": "Rich Men North of Richmond",
    "artist": "Oliver Anthony Music",
    "source": "https://en.wikipedia.org/wiki/List_of_Billboard_Hot_100_number_ones_of_2023",
    "row_index": 16
  },
  {
    "year": 2023,
    "issue_date": "2023-09-09",
    "week": "2023-09-09",
    "song": "I Remember Everything",
    "artist": "Zach Bryan featuring Kacey Musgraves",
    "source": "https://en.wikipedia.org/wiki/List_of_Billboard_Hot_100_number_ones_of_2023",
    "row_index": 17
  },
  {
    "year": 2023,
    "issue_date": "2023-09-16",
    "week": "2023-09-16",
    "song": "Paint the Town Red",
    "artist": "Doja Cat",
    "source": "https://en.wikipedia.org/wiki/List_of_Billboard_Hot_100_number_ones_of_2023",
    "row_index": 18
  },
  {
    "year": 2023,
    "issue_date": "2023-09-23",
    "week": "2023-09-23",
    "song": "Vampire",
    "artist": "Olivia Rodrigo",
    "source": "https://en.wikipedia.org/wiki/List_of_Billboard_Hot_100_number_ones_of_2023",
    "row_index": 19
  },
  {
    "year": 2023,
    "issue_date": "2023-09-30",
    "week": "2023-09-30",
    "song": "Slime You Out",
    "artist": "Drake featuring SZA",
    "source": "https://en.wikipedia.org/wiki/List_of_Billboard_Hot_100_number_ones_of_2023",
    "row_index": 20
  },
  {
    "year": 2023,
    "issue_date": "2023-10-07",
    "week": "2023-10-07",
    "song": "Paint the Town Red",
    "artist": "Doja Cat",
    "source": "https://en.wikipedia.org/wiki/List_of_Billboard_Hot_100_number_ones_of_2023",
    "row_index": 21
  },
  {
    "year": 2023,
    "issue_date": "2023-10-21",
    "week": "2023-10-21",
    "song": "First Person Shooter",
    "artist": "Drake featuring J. Cole",
    "source": "https://en.wikipedia.org/wiki/List_of_Billboard_Hot_100_number_ones_of_2023",
    "row_index": 22
  },
  {
    "year": 2023,
    "issue_date": "2023-10-28",
    "week": "2023-10-28",
    "song": "Cruel Summer",
    "artist": "Taylor Swift",
    "source": "https://en.wikipedia.org/wiki/List_of_Billboard_Hot_100_number_ones_of_2023",
    "row_index": 23
  },
  {
    "year": 2023,
    "issue_date": "2023-11-11",
    "week": "2023-11-11",
    "song": "Is It Over Now?",
    "artist": "[ 92 ] [ 6 ]",
    "source": "https://en.wikipedia.org/wiki/List_of_Billboard_Hot_100_number_ones_of_2023",
    "row_index": 24
  },
  {
    "year": 2023,
    "issue_date": "2023-11-18",
    "week": "2023-11-18",
    "song": "Cruel Summer",
    "artist": "[ 93 ] [ 94 ]",
    "source": "https://en.wikipedia.org/wiki/List_of_Billboard_Hot_100_number_ones_of_2023",
    "row_index": 25
  },
  {
    "year": 2023,
    "issue_date": "2023-12-02",
    "week": "2023-12-02",
    "song": "Lovin on Me",
    "artist": "Jack Harlow",
    "source": "https://en.wikipedia.org/wiki/List_of_Billboard_Hot_100_number_ones_of_2023",
    "row_index": 26
  },
  {
    "year": 2023,
    "issue_date": "2023-12-09",
    "week": "2023-12-09",
    "song": "Rockin' Around the Christmas Tree",
    "artist": "Brenda Lee",
    "source": "https://en.wikipedia.org/wiki/List_of_Billboard_Hot_100_number_ones_of_2023",
    "row_index": 27
  },
  {
    "year": 2023,
    "issue_date": "2023-12-23",
    "week": "2023-12-23",
    "song": "All I Want for Christmas Is You",
    "artist": "Mariah Carey",
    "source": "https://en.wikipedia.org/wiki/List_of_Billboard_Hot_100_number_ones_of_2023",
    "row_index": 28
  }
]